agent/__init__.py
agent/explainer.py
agent/models.py
audit/__init__.py
audit/models.py
audit/cost/__init__.py
audit/cost/ec2_cost_audit.py
audit/cost/s3_cost_audit.py
audit/security/__init__.py
audit/security/ec2_security_audit.py
audit/security/s3_security_audit.py
cli/__init__.py
cli/aws_utils.py
cli/check_config.py
cli/explain.py
cli/main.py
cli/report.py
cli/scan.py
correlate/__init__.py
correlate/correlator.py
kenning/__init__.py
kenning_cli-1.2.2.dist-info/licenses/LICENSE
reports/__init__.py
reports/markdown_writer.py
kenning_cli-1.2.2.dist-info/METADATA
kenning_cli-1.2.2.dist-info/WHEEL
kenning_cli-1.2.2.dist-info/entry_points.txt
kenning_cli-1.2.2.dist-info/top_level.txt
kenning_cli-1.2.2.dist-info/RECORD
