Metadata-Version: 2.4
Name: kenning-cli
Version: 1.2.2
Summary: AI-powered contextual risk analysis tool for AWS infrastructure - identifies compound security and cost risks
Home-page: https://github.com/kenningproject/kenning-cli
Author: Kenning Project
Author-email: Kenning Project <info@kenningproject.com>
Maintainer-email: Kenning Project <info@kenningproject.com>
License-Expression: MIT
Project-URL: Homepage, https://github.com/kenningproject/kenning-cli
Project-URL: Repository, https://github.com/kenningproject/kenning-cli
Project-URL: Documentation, https://github.com/kenningproject/kenning-cli#readme
Project-URL: Bug Tracker, https://github.com/kenningproject/kenning-cli/issues
Keywords: aws,security,cost-optimization,devops,cloud,cli,ai,risk-analysis
Classifier: Development Status :: 5 - Production/Stable
Classifier: Intended Audience :: Developers
Classifier: Intended Audience :: System Administrators
Classifier: Intended Audience :: Information Technology
Classifier: Operating System :: OS Independent
Classifier: Programming Language :: Python :: 3
Classifier: Programming Language :: Python :: 3.9
Classifier: Programming Language :: Python :: 3.10
Classifier: Programming Language :: Python :: 3.11
Classifier: Programming Language :: Python :: 3.12
Classifier: Topic :: Security
Classifier: Topic :: System :: Systems Administration
Classifier: Topic :: System :: Monitoring
Classifier: Topic :: Utilities
Classifier: Environment :: Console
Classifier: Natural Language :: English
Requires-Python: >=3.9
License-File: LICENSE
Requires-Dist: boto3
Requires-Dist: click
Requires-Dist: colorama
Requires-Dist: python-dotenv
Requires-Dist: pydantic
Requires-Dist: ollama
Provides-Extra: dev
Requires-Dist: pytest; extra == "dev"
Requires-Dist: moto; extra == "dev"
Requires-Dist: flake8; extra == "dev"
Requires-Dist: black; extra == "dev"
Requires-Dist: isort; extra == "dev"
Dynamic: author
Dynamic: home-page
Dynamic: license-file
Dynamic: requires-python
